pydantic_django/__init__.py
pydantic_django/fields.py
pydantic_django/main.py
pydantic_django/py.typed
tests/__init__.py
tests/conftest.py
tests/test_fields.py
tests/test_main.py
tests/test_queries.py
tests/test_relations.py
tests/test_schemas.py
tests/testapp/__init__.py
tests/testapp/apps.py
tests/testapp/fields.py
tests/testapp/manage.py
tests/testapp/models.py
tests/testapp/settings.py
tests/testapp/project/__init__.py
tests/testapp/project/asgi.py
tests/testapp/project/settings.py
tests/testapp/project/urls.py
tests/testapp/project/wsgi.py
pydantic_django-0.1.0.dist-info/LICENSE
pydantic_django-0.1.0.dist-info/METADATA
pydantic_django-0.1.0.dist-info/WHEEL
pydantic_django-0.1.0.dist-info/top_level.txt
pydantic_django-0.1.0.dist-info/RECORD
